_version.py
claimed.py
scripts/claimed
claimed_cli-0.1.6.dist-info/LICENSE
claimed_cli-0.1.6.dist-info/METADATA
claimed_cli-0.1.6.dist-info/WHEEL
claimed_cli-0.1.6.dist-info/entry_points.txt
claimed_cli-0.1.6.dist-info/top_level.txt
claimed_cli-0.1.6.dist-info/RECORD
