Metadata-Version: 2.1
Name: claimed-cli
Version: 0.1.6
Summary: CLI tool for running CLAIMED operators locally
Author-email: The CLAIMED authors <claimed-framework@proton.me>
Maintainer: Benedikt Blumenstiel
Maintainer-email: Romeo Kienzler <claimed-framework@proton.me>
Project-URL: Homepage, https://github.com/claimed-framework/cli
Project-URL: Bug Tracker, https://github.com/claimed-framework/cli/issues
Keywords: CLAIMED,cli
Classifier: Programming Language :: Python :: 3
Classifier: License :: OSI Approved :: Apache Software License
Classifier: Operating System :: OS Independent
Requires-Python: >=3.7
License-File: LICENSE
